cxxpy/__init__.py
cxxpy/setup.py
examples/__init__.py
examples/BayesianDesign/00_cook_raw_data.py
examples/BayesianDesign/0_mining_csd_complexes.py
examples/BayesianDesign/1_data_convert.py
examples/BayesianDesign/__init__.py
examples/BayesianDesign/data_convert.py
examples/BayesianDesign/data_process.py
examples/BayesianDesign/get_data.py
examples/BayesianDesign/machines_config.py
examples/BayesianDesign/normalize_target.py
examples/BayesianDesign/repair_dataset.py
examples/BayesianDesign/run_complex_train.py
examples/BayesianDesign/run_cv.py
examples/BayesianDesign/test.py
examples/BayesianDesign/test_SclogK_data.py
examples/BayesianDesign/test_nested_tensor.py
examples/BayesianDesign/xtb_filter.py
examples/BayesianDesign/PhenMol/__init__.py
examples/BayesianDesign/PhenMol/pair_link.py
examples/BayesianDesign/arch/__init__.py
examples/BayesianDesign/arch/_example.py
examples/BayesianDesign/modules/__init__.py
examples/BayesianDesign/modules/custom_json.py
examples/BayesianDesign/modules/data_mining.py
examples/BayesianDesign/modules/model.py
examples/BayesianDesign/modules/cook_raw_data/__init__.py
examples/BayesianDesign/modules/cook_raw_data/cook_BetaG.py
examples/BayesianDesign/modules/cook_raw_data/cook_SclogK.py
examples/BayesianDesign/modules/data_process/SclogK.py
examples/BayesianDesign/modules/data_process/__init__.py
examples/BayesianDesign/modules/data_process/complexes.py
examples/BayesianDesign/modules/data_process/gibbs_beta.py
examples/BayesianDesign/modules/data_process/pairs.py
examples/BayesianDesign/modules/data_process/utils.py
examples/BayesianDesign/plots/__init__.py
examples/BayesianDesign/plots/cbond_combine.py
examples/ChineseMedical/__init__.py
examples/ChineseMedical/analysis.py
examples/DAC/__init__.py
examples/DAC/co2adsorpTGA.py
examples/mol_assemble/__init__.py
examples/mol_assemble/assemble.py
examples/mol_assemble/xjz/__init__.py
examples/mol_assemble/xjz/fenzizuzhuang.py
examples/nuclear_medical/__init__.py
hotpot_zzy-0.5.2.1.dist-info/LICENSE
hotpot_zzy-0.5.2.1.dist-info/METADATA
hotpot_zzy-0.5.2.1.dist-info/WHEEL
hotpot_zzy-0.5.2.1.dist-info/entry_points.txt
hotpot_zzy-0.5.2.1.dist-info/top_level.txt
hotpot_zzy-0.5.2.1.dist-info/RECORD
