Metadata-Version: 2.2
Name: hotpot-zzy
Version: 0.5.2.1
Summary: A python package designed to communicate among various chemical and materials calculational tools
Home-page: https://github.com/Zhang-Zhiyuan-zzy/hotpot
Author: Zhiyuan Zhang
Author-email: Zhiyuan Zhang <ZhiyuanZhang_scu@163.com>, Yue Dong <1320801310@qq.com>, Yuqing Qiu <2022223070045@stu.scu.edu.cn>
Project-URL: Homepage, https://github.com/Zhang-Zhiyuan-zzy/hotpot
Classifier: Programming Language :: Python :: 3.9
Classifier: License :: OSI Approved :: MIT License
Classifier: Operating System :: Unix
License-File: LICENSE
Requires-Dist: numpy
Requires-Dist: pandas
Requires-Dist: thermo
Requires-Dist: cclib
Requires-Dist: tqdm
Requires-Dist: rdkit
Requires-Dist: psutil
Requires-Dist: rdkit
Requires-Dist: matplotlib
Requires-Dist: scikit-learn
Requires-Dist: torch
Requires-Dist: torch-geometric
Requires-Dist: gpytorch
Requires-Dist: shap
Requires-Dist: seaborn
Requires-Dist: xgboost
Requires-Dist: pyspark
Requires-Dist: openpyxl
Dynamic: author
Dynamic: home-page
